{
  "info": {
    "_postman_id": "e37fef33-76f8-4556-83dd-f233e1d359ea",
    "name": "SkillSwap API",
    "schema": "https://schema.getpostman.com/json/collection/v2.1.0/collection.json",
    "_exporter_id": "30912480"
  },
  "item": [
    {
      "name": "Users",
      "item": [
        {
          "name": "Get All Users",
          "request": {
            "method": "GET",
            "header": [
              {
                "key": "Content-Type",
                "value": "application/json",
                "disabled": false
              }
            ],
            "url": {
              "raw": "{{baseUrl}}/users?page=1&limit=2",
              "host": [
                "{{baseUrl}}"
              ],
              "path": [
                "users"
              ],
              "query": [
                {
                  "key": "page",
                  "value": "1",
                  "type": "text"
                },
                {
                  "key": "limit",
                  "value": "2",
                  "type": "text"
                }
              ]
            },
            "description": "Retrieves a list of all users in the system."
          },
          "response": []
        },
        {
          "name": "Get User by ID",
          "request": {
            "method": "GET",
            "header": [],
            "url": {
              "raw": "{{baseUrl}}/users/:id",
              "host": [
                "{{baseUrl}}"
              ],
              "path": [
                "users",
                ":id"
              ],
              "variable": [
                {
                  "key": "id",
                  "value": "704607ec-98c0-4809-82b0-a29b87154104"
                }
              ]
            },
            "description": "Retrieves a single user by their unique ID."
          },
          "response": []
        },
        {
          "name": "Update me",
          "request": {
            "auth": {
              "type": "bearer",
              "bearer": [
                {
                  "key": "token",
                  "value": "{{jwt-access}}",
                  "type": "string"
                }
              ]
            },
            "method": "PATCH",
            "header": [
              {
                "key": "Content-Type",
                "value": "application/json",
                "disabled": false
              }
            ],
            "body": {
              "mode": "raw",
              "raw": "{\r\n  \"name\": \"Bob Martinez\",\r\n  \"email\": \"bob.martinez@example.com\",\r\n  \"about\": \"Full-stack engineer with a passion for clean architecture.\",\r\n  \"birthdate\": \"1990-03-22\",\r\n  \"city\": \"Hamburg\",\r\n  \"gender\": \"MALE\",\r\n  \"wantToLearn\": [\"f81fc9b4-fbb5-46f7-a024-36969178c0b8\"]\r\n}",
              "options": {
                "raw": {
                  "language": "json"
                }
              }
            },
            "url": {
              "raw": "{{baseUrl}}/users/me",
              "host": [
                "{{baseUrl}}"
              ],
              "path": [
                "users",
                "me"
              ]
            },
            "description": "Updates an existing user's name and email by their unique ID."
          },
          "response": []
        },
        {
          "name": "Get me",
          "request": {
            "auth": {
              "type": "bearer",
              "bearer": [
                {
                  "key": "token",
                  "value": "{{jwt-access}}",
                  "type": "string"
                }
              ]
            },
            "method": "GET",
            "header": [],
            "url": {
              "raw": "{{baseUrl}}/users/me",
              "host": [
                "{{baseUrl}}"
              ],
              "path": [
                "users",
                "me"
              ]
            }
          },
          "response": []
        },
        {
          "name": "Update password",
          "request": {
            "auth": {
              "type": "bearer",
              "bearer": [
                {
                  "key": "token",
                  "value": "{{jwt-access}}",
                  "type": "string"
                }
              ]
            },
            "method": "PATCH",
            "header": [],
            "body": {
              "mode": "raw",
              "raw": "{\r\n    \"oldPassword\": \"SecurePass123!\",\r\n    \"newPassword\": \"SecurePass123!\"\r\n}",
              "options": {
                "raw": {
                  "language": "json"
                }
              }
            },
            "url": {
              "raw": "{{baseUrl}}/users/me/password",
              "host": [
                "{{baseUrl}}"
              ],
              "path": [
                "users",
                "me",
                "password"
              ]
            }
          },
          "response": []
        }
      ],
      "event": [
        {
          "listen": "prerequest",
          "script": {
            "type": "text/javascript",
            "packages": {},
            "requests": {},
            "exec": [
              ""
            ]
          }
        },
        {
          "listen": "test",
          "script": {
            "type": "text/javascript",
            "packages": {},
            "requests": {},
            "exec": [
              ""
            ]
          }
        }
      ]
    },
    {
      "name": "Auth",
      "item": [
        {
          "name": "Register",
          "event": [
            {
              "listen": "test",
              "script": {
                "exec": [
                  "const jsonData = pm.response.json();\r",
                  "pm.collectionVariables.set(\"jwt-access\", jsonData.accessToken);"
                ],
                "type": "text/javascript",
                "packages": {},
                "requests": {}
              }
            }
          ],
          "request": {
            "method": "POST",
            "header": [
              {
                "key": "Content-Type",
                "value": "application/json",
                "disabled": false
              }
            ],
            "body": {
              "mode": "raw",
              "raw": "{\r\n  \"name\": \"Orban Joe\",\r\n  \"email\": \"alice.johnson@gmailingo.com\",\r\n  \"password\": \"SecurePass123!\",\r\n  \"about\": \"Passionate developer eager to learn new technologies.\",\r\n  \"birthdate\": \"1995-06-15\",\r\n  \"city\": \"Berlin\",\r\n  \"gender\": \"MALE\",\r\n  \"wantToLearn\": [\"f81fc9b4-fbb5-46f7-a024-36969178c0b8\"]\r\n}"
            },
            "url": {
              "raw": "{{baseUrl}}/auth/register",
              "host": [
                "{{baseUrl}}"
              ],
              "path": [
                "auth",
                "register"
              ]
            }
          },
          "response": []
        },
        {
          "name": "Refresh token",
          "event": [
            {
              "listen": "test",
              "script": {
                "exec": [
                  "const jsonData = pm.response.json();\r",
                  "pm.collectionVariables.set(\"jwt-access\", jsonData.accessToken);"
                ],
                "type": "text/javascript",
                "packages": {},
                "requests": {}
              }
            }
          ],
          "request": {
            "method": "POST",
            "header": [],
            "url": {
              "raw": "{{baseUrl}}/auth/refresh",
              "host": [
                "{{baseUrl}}"
              ],
              "path": [
                "auth",
                "refresh"
              ]
            }
          },
          "response": []
        },
        {
          "name": "Login",
          "event": [
            {
              "listen": "test",
              "script": {
                "exec": [
                  "const jsonData = pm.response.json();\r",
                  "pm.collectionVariables.set(\"jwt-access\", jsonData.accessToken);"
                ],
                "type": "text/javascript",
                "packages": {},
                "requests": {}
              }
            }
          ],
          "request": {
            "method": "POST",
            "header": [],
            "body": {
              "mode": "raw",
              "raw": "{\r\n    \"email\": \"alice.johnson@gmailf.com\",\r\n    \"password\": \"SecurePass123!\"\r\n}",
              "options": {
                "raw": {
                  "language": "json"
                }
              }
            },
            "url": {
              "raw": "{{baseUrl}}/auth/login",
              "host": [
                "{{baseUrl}}"
              ],
              "path": [
                "auth",
                "login"
              ]
            }
          },
          "response": []
        },
        {
          "name": "Logout",
          "request": {
            "auth": {
              "type": "bearer",
              "bearer": [
                {
                  "key": "token",
                  "value": "{{jwt-access}}",
                  "type": "string"
                }
              ]
            },
            "method": "POST",
            "header": [],
            "body": {
              "mode": "raw",
              "raw": "{\r\n    \"email\": \"alice.johnson@gmail.com\",\r\n    \"password\": \"SecurePass123!\"\r\n}"
            },
            "url": {
              "raw": "{{baseUrl}}/auth/logout",
              "host": [
                "{{baseUrl}}"
              ],
              "path": [
                "auth",
                "logout"
              ]
            }
          },
          "response": []
        }
      ]
    },
    {
      "name": "Files",
      "item": [
        {
          "name": "Upload file",
          "request": {
            "auth": {
              "type": "bearer",
              "bearer": [
                {
                  "key": "token",
                  "value": "{{jwt-access}}",
                  "type": "string"
                }
              ]
            },
            "method": "POST",
            "header": [],
            "body": {
              "mode": "formdata",
              "formdata": [
                {
                  "key": "file",
                  "type": "file"
                }
              ]
            },
            "url": {
              "raw": "{{baseUrl}}/upload",
              "host": [
                "{{baseUrl}}"
              ],
              "path": [
                "upload"
              ]
            }
          },
          "response": []
        }
      ]
    },
    {
      "name": "Skills",
      "item": [
        {
          "name": "Create skill",
          "request": {
            "auth": {
              "type": "bearer",
              "bearer": [
                {
                  "key": "token",
                  "value": "{{jwt-access}}",
                  "type": "string"
                }
              ]
            },
            "method": "POST",
            "header": [],
            "body": {
              "mode": "raw",
              "raw": "{\r\n  \"title\": \"React Native для начинающих\",\r\n  \"description\": \"Научу основам React Native\",\r\n  \"category\": \"f81fc9b4-fbb5-46f7-a024-36969178c0b8\",\r\n  \"images\": [\r\n    \"/uploads/cbff6986-d1b3-400b-b45d-c90922e54b83.jpg\"\r\n  ]\r\n}",
              "options": {
                "raw": {
                  "language": "json"
                }
              }
            },
            "url": {
              "raw": "{{baseUrl}}/skills",
              "host": [
                "{{baseUrl}}"
              ],
              "path": [
                "skills"
              ]
            }
          },
          "response": []
        },
        {
          "name": "Get skills",
          "request": {
            "method": "GET",
            "header": [],
            "url": {
              "raw": "{{baseUrl}}/skills?page=1&limit=10&search=nest",
              "host": [
                "{{baseUrl}}"
              ],
              "path": [
                "skills"
              ],
              "query": [
                {
                  "key": "page",
                  "value": "1"
                },
                {
                  "key": "limit",
                  "value": "10"
                },
                {
                  "key": "search",
                  "value": "nest"
                }
              ]
            }
          },
          "response": []
        },
        {
          "name": "Add to favorite",
          "request": {
            "auth": {
              "type": "bearer",
              "bearer": [
                {
                  "key": "token",
                  "value": "{{jwt-access}}",
                  "type": "string"
                }
              ]
            },
            "method": "POST",
            "header": [],
            "url": {
              "raw": "{{baseUrl}}/skills/:id/favorite",
              "host": [
                "{{baseUrl}}"
              ],
              "path": [
                "skills",
                ":id",
                "favorite"
              ],
              "variable": [
                {
                  "key": "id",
                  "value": "39b92df9-13a3-41d2-9721-887aaa237e5d"
                }
              ]
            }
          },
          "response": []
        },
        {
          "name": "Update skill",
          "request": {
            "auth": {
              "type": "bearer",
              "bearer": [
                {
                  "key": "token",
                  "value": "{{jwt-access}}",
                  "type": "string"
                }
              ]
            },
            "method": "PATCH",
            "header": [],
            "body": {
              "mode": "raw",
              "raw": "{\r\n    \"title\": \"Test\",\r\n    \"description\": \"Test\",\r\n    \"category\": \"b6366f20-8cb6-4ad2-850d-e4100897696c\",\r\n    \"images\": []\r\n}",
              "options": {
                "raw": {
                  "language": "json"
                }
              }
            },
            "url": {
              "raw": "{{baseUrl}}/skills/:id",
              "host": [
                "{{baseUrl}}"
              ],
              "path": [
                "skills",
                ":id"
              ],
              "variable": [
                {
                  "key": "id",
                  "value": "f8423795-919b-4472-9e99-efbde1571c26"
                }
              ]
            }
          },
          "response": []
        },
        {
          "name": "Delete skill",
          "request": {
            "auth": {
              "type": "bearer",
              "bearer": [
                {
                  "key": "token",
                  "value": "{{jwt-access}}",
                  "type": "string"
                }
              ]
            },
            "method": "DELETE",
            "header": [],
            "url": {
              "raw": "{{baseUrl}}/skills/:id",
              "host": [
                "{{baseUrl}}"
              ],
              "path": [
                "skills",
                ":id"
              ],
              "variable": [
                {
                  "key": "id",
                  "value": "b2829d29-7e22-4caf-a2cf-ea33b050c770"
                }
              ]
            }
          },
          "response": []
        }
      ]
    }
  ],
  "event": [
    {
      "listen": "prerequest",
      "script": {
        "type": "text/javascript",
        "packages": {},
        "requests": {},
        "exec": [
          ""
        ]
      }
    },
    {
      "listen": "test",
      "script": {
        "type": "text/javascript",
        "packages": {},
        "requests": {},
        "exec": [
          ""
        ]
      }
    }
  ],
  "variable": [
    {
      "key": "baseUrl",
      "value": ""
    },
    {
      "key": "jwt-access",
      "value": ""
    }
  ]
}